README.rst
setup.py
pinocchio/__init__.py
pinocchio/decorator.py
pinocchio/figleaf_sections.py
pinocchio/output_save.py
pinocchio/spec.py
pinocchio/stopwatch.py
pinocchio.egg-info/PKG-INFO
pinocchio.egg-info/SOURCES.txt
pinocchio.egg-info/dependency_links.txt
pinocchio.egg-info/entry_points.txt
pinocchio.egg-info/requires.txt
pinocchio.egg-info/top_level.txt